amazon/__init__.py
amazon/constant.py
amazon/entities.py
amazon/exception.py
amazon/paapi.py
amazon_paapi5-1.1.2.dist-info/LICENSE
amazon_paapi5-1.1.2.dist-info/METADATA
amazon_paapi5-1.1.2.dist-info/WHEEL
amazon_paapi5-1.1.2.dist-info/top_level.txt
amazon_paapi5-1.1.2.dist-info/RECORD
