Metadata-Version: 2.1
Name: amazon-paapi5
Version: 1.1.2
Summary: Amazon Product Advertising API 5.0 wrapper for Python
Home-page: https://github.com/alefiori82/amazon-paapi5
Author: Alessandro Fiori
Author-email: alessandro.fiori@gmail.com
License: GPL-3.0
Platform: UNKNOWN
Classifier: Programming Language :: Python
Classifier: License :: OSI Approved :: GNU General Public License v3 (GPLv3)
Classifier: Operating System :: OS Independent
Requires-Python: >=3.6
